MANIFEST.in
README.md
README.rst
setup.py
rpcdb/__init__.py
rpcdb/__main__.py
rpcdb.egg-info/PKG-INFO
rpcdb.egg-info/SOURCES.txt
rpcdb.egg-info/dependency_links.txt
rpcdb.egg-info/requires.txt
rpcdb.egg-info/top_level.txt
rpcdb/client/__init__.py
rpcdb/client/base.py
rpcdb/client/calwidget.py
rpcdb/client/client_proxy.py
rpcdb/client/fields.py
rpcdb/client/models.py
rpcdb/server/__init__.py
rpcdb/server/controller.py
rpcdb/server/rpcserver.py
rpcdb/server/sqlconnection.py
rpcdb/utils/__init__.py
rpcdb/utils/chatclient.py
rpcdb/utils/console.py
rpcdb/utils/util.py