Metadata-Version: 1.0
Name: rpcdb
Version: 0.0.5
Summary: A multiplatform mysql framework for client-server apps
Home-page: https://github.com/abiiranathan/rpcdb.git
Author: Dr Abiira Nathan
Author-email: nabiira2by2@gmail.com
License: GPL-3
Keywords: mysql database python Abiira Nathan framework rpcdb tkinter relational mapper
Platform: Windows 7
Platform: Windows 8
Platform: Windows 10
Platform: Linux/Unix
